repoclient/__init__.py
repoclient/__main__.py
repoclient/exception.py
repoclient/models.py
repoclient/pagination.py
repoclient/util.py
repoclient/__pycache__/__init__.cpython-311.pyc
repoclient/models/__init__.py
repoclient/models/base_model.py
repoclient/models/common.py
repoclient/models/entitlement.py
repoclient/models/format.py
repoclient/models/handler.py
repoclient/models/query.py
repoclient/models/upload_session.py
repoclient/models/user.py
repoclient-1.1.1.dist-info/METADATA
repoclient-1.1.1.dist-info/WHEEL
repoclient-1.1.1.dist-info/top_level.txt
repoclient-1.1.1.dist-info/RECORD
